eero_adguard_sync/__init__.py
eero_adguard_sync/__main__.py
eero_adguard_sync/main.py
eero_adguard_sync/client/__init__.py
eero_adguard_sync/client/adguard.py
eero_adguard_sync/client/eero.py
eero_adguard_sync/commands/__init__.py
eero_adguard_sync/commands/clear.py
eero_adguard_sync/commands/sync.py
eero_adguard_sync/models/__init__.py
eero_adguard_sync/models/adguard/__init__.py
eero_adguard_sync/models/adguard/client_device.py
eero_adguard_sync/models/adguard/credential_set.py
eero_adguard_sync/models/dhcp/__init__.py
eero_adguard_sync/models/dhcp/client_device.py
eero_adguard_sync/models/dhcp/client_table.py
eero_adguard_sync/models/eero/__init__.py
eero_adguard_sync/models/eero/client_device.py
eero_adguard_sync/models/eero/network_device.py
eero_adguard_sync/utils/__init__.py
eero_adguard_sync/utils/app_paths.py
eero_adguard_sync/utils/base_url_session.py
eero_adguard_sync-0.3.2.dist-info/LICENSE
eero_adguard_sync-0.3.2.dist-info/METADATA
eero_adguard_sync-0.3.2.dist-info/WHEEL
eero_adguard_sync-0.3.2.dist-info/entry_points.txt
eero_adguard_sync-0.3.2.dist-info/top_level.txt
eero_adguard_sync-0.3.2.dist-info/RECORD
