Metadata-Version: 2.1
Name: eero-adguard-sync
Version: 0.3.2
Summary: Sync Eero DHCP client list to AdGuard Home
Home-page: https://github.com/amickael/eero-adguard-sync
Author: Andrew Mickael
Author-email: andrew.mickael@gmail.com
License: UNKNOWN
Platform: UNKNOWN
Classifier: Programming Language :: Python :: 3
Classifier: License :: OSI Approved :: MIT License
Classifier: Operating System :: OS Independent
Requires-Python: >=3.7
License-File: LICENSE
Requires-Dist: requests (==2.27.1)
Requires-Dist: appdata (==2.1.1)
Requires-Dist: click (==8.0.3)
Requires-Dist: macaddress (==1.1.3)
Requires-Dist: eero (<=0.0.3,>=0.0.2)
